[
  {
    "inputs": [
      {
        "internalType": "contract IKOAccessControlsLookup",
        "name": "_accessControls",
        "type": "address"
      },
      {
        "internalType": "contract IKODAV3",
        "name": "_koda",
        "type": "address"
      },
      {
        "internalType": "address",
        "name": "_platformAccount",
        "type": "address"
      }
    ],
    "stateMutability": "nonpayable",
    "type": "constructor"
  },
  {
    "anonymous": false,
    "inputs": [
      {
        "indexed": false,
        "internalType": "uint256",
        "name": "_minBidAmount",
        "type": "uint256"
      }
    ],
    "name": "AdminUpdateMinBidAmount",
    "type": "event"
  },
  {
    "anonymous": false,
    "inputs": [
      {
        "indexed": false,
        "internalType": "uint256",
        "name": "_modulo",
        "type": "uint256"
      }
    ],
    "name": "AdminUpdateModulo",
    "type": "event"
  },
  {
    "anonymous": false,
    "inputs": [
      {
        "indexed": false,
        "internalType": "uint256",
        "name": "_platformPrimarySaleCommission",
        "type": "uint256"
      }
    ],
    "name": "AdminUpdatePlatformPrimarySaleCommission",
    "type": "event"
  },
  {
    "anonymous": false,
    "inputs": [
      {
        "indexed": false,
        "internalType": "uint128",
        "name": "_reserveAuctionBidExtensionWindow",
        "type": "uint128"
      }
    ],
    "name": "AdminUpdateReserveAuctionBidExtensionWindow",
    "type": "event"
  },
  {
    "anonymous": false,
    "inputs": [
      {
        "indexed": false,
        "internalType": "uint128",
        "name": "_reserveAuctionLengthOnceReserveMet",
        "type": "uint128"
      }
    ],
    "name": "AdminUpdateReserveAuctionLengthOnceReserveMet",
    "type": "event"
  },
  {
    "anonymous": false,
    "inputs": [
      {
        "indexed": true,
        "internalType": "uint256",
        "name": "_editionId",
        "type": "uint256"
      },
      {
        "indexed": true,
        "internalType": "address",
        "name": "_bidder",
        "type": "address"
      },
      {
        "indexed": false,
        "internalType": "uint256",
        "name": "_amount",
        "type": "uint256"
      }
    ],
    "name": "BidPlacedOnReserveAuction",
    "type": "event"
  },
  {
    "anonymous": false,
    "inputs": [
      {
        "indexed": false,
        "internalType": "uint256",
        "name": "_editionId",
        "type": "uint256"
      },
      {
        "indexed": true,
        "internalType": "address",
        "name": "_bidder",
        "type": "address"
      },
      {
        "indexed": false,
        "internalType": "uint128",
        "name": "_bid",
        "type": "uint128"
      }
    ],
    "name": "BidWithdrawnFromReserveAuction",
    "type": "event"
  },
  {
    "anonymous": false,
    "inputs": [
      {
        "indexed": true,
        "internalType": "uint256",
        "name": "_editionId",
        "type": "uint256"
      },
      {
        "indexed": false,
        "internalType": "uint128",
        "name": "_startDate",
        "type": "uint128"
      }
    ],
    "name": "EditionAcceptingOffer",
    "type": "event"
  },
  {
    "anonymous": false,
    "inputs": [
      {
        "indexed": true,
        "internalType": "uint256",
        "name": "_editionId",
        "type": "uint256"
      },
      {
        "indexed": true,
        "internalType": "uint256",
        "name": "_tokenId",
        "type": "uint256"
      },
      {
        "indexed": true,
        "internalType": "address",
        "name": "_bidder",
        "type": "address"
      },
      {
        "indexed": false,
        "internalType": "uint256",
        "name": "_amount",
        "type": "uint256"
      }
    ],
    "name": "EditionBidAccepted",
    "type": "event"
  },
  {
    "anonymous": false,
    "inputs": [
      {
        "indexed": true,
        "internalType": "uint256",
        "name": "_editionId",
        "type": "uint256"
      },
      {
        "indexed": true,
        "internalType": "address",
        "name": "_bidder",
        "type": "address"
      },
      {
        "indexed": false,
        "internalType": "uint256",
        "name": "_amount",
        "type": "uint256"
      }
    ],
    "name": "EditionBidPlaced",
    "type": "event"
  },
  {
    "anonymous": false,
    "inputs": [
      {
        "indexed": true,
        "internalType": "uint256",
        "name": "_editionId",
        "type": "uint256"
      },
      {
        "indexed": true,
        "internalType": "address",
        "name": "_bidder",
        "type": "address"
      },
      {
        "indexed": false,
        "internalType": "uint256",
        "name": "_amount",
        "type": "uint256"
      }
    ],
    "name": "EditionBidRejected",
    "type": "event"
  },
  {
    "anonymous": false,
    "inputs": [
      {
        "indexed": true,
        "internalType": "uint256",
        "name": "_editionId",
        "type": "uint256"
      },
      {
        "indexed": true,
        "internalType": "address",
        "name": "_bidder",
        "type": "address"
      }
    ],
    "name": "EditionBidWithdrawn",
    "type": "event"
  },
  {
    "anonymous": false,
    "inputs": [
      {
        "indexed": true,
        "internalType": "uint256",
        "name": "_editionId",
        "type": "uint256"
      }
    ],
    "name": "EditionDeListed",
    "type": "event"
  },
  {
    "anonymous": false,
    "inputs": [
      {
        "indexed": true,
        "internalType": "uint256",
        "name": "_editionId",
        "type": "uint256"
      },
      {
        "indexed": false,
        "internalType": "uint256",
        "name": "_price",
        "type": "uint256"
      },
      {
        "indexed": false,
        "internalType": "uint256",
        "name": "_startDate",
        "type": "uint256"
      }
    ],
    "name": "EditionListed",
    "type": "event"
  },
  {
    "anonymous": false,
    "inputs": [
      {
        "indexed": true,
        "internalType": "uint256",
        "name": "_editionId",
        "type": "uint256"
      },
      {
        "indexed": false,
        "internalType": "uint256",
        "name": "_reservePrice",
        "type": "uint256"
      },
      {
        "indexed": false,
        "internalType": "uint128",
        "name": "_startDate",
        "type": "uint128"
      }
    ],
    "name": "EditionListedForReserveAuction",
    "type": "event"
  },
  {
    "anonymous": false,
    "inputs": [
      {
        "indexed": true,
        "internalType": "uint256",
        "name": "_editionId",
        "type": "uint256"
      },
      {
        "indexed": false,
        "internalType": "uint256",
        "name": "_price",
        "type": "uint256"
      }
    ],
    "name": "EditionPriceChanged",
    "type": "event"
  },
  {
    "anonymous": false,
    "inputs": [
      {
        "indexed": true,
        "internalType": "uint256",
        "name": "_editionId",
        "type": "uint256"
      },
      {
        "indexed": true,
        "internalType": "uint256",
        "name": "_tokenId",
        "type": "uint256"
      },
      {
        "indexed": true,
        "internalType": "address",
        "name": "_buyer",
        "type": "address"
      },
      {
        "indexed": false,
        "internalType": "uint256",
        "name": "_price",
        "type": "uint256"
      }
    ],
    "name": "EditionPurchased",
    "type": "event"
  },
  {
    "anonymous": false,
    "inputs": [
      {
        "indexed": true,
        "internalType": "uint256",
        "name": "_editionId",
        "type": "uint256"
      },
      {
        "indexed": true,
        "internalType": "uint256",
        "name": "_tokenId",
        "type": "uint256"
      },
      {
        "indexed": true,
        "internalType": "address",
        "name": "_buyer",
        "type": "address"
      },
      {
        "indexed": false,
        "internalType": "uint256",
        "name": "_price",
        "type": "uint256"
      },
      {
        "indexed": false,
        "internalType": "uint16",
        "name": "_currentStep",
        "type": "uint16"
      }
    ],
    "name": "EditionSteppedSaleBuy",
    "type": "event"
  },
  {
    "anonymous": false,
    "inputs": [
      {
        "indexed": true,
        "internalType": "uint256",
        "name": "_editionId",
        "type": "uint256"
      },
      {
        "indexed": false,
        "internalType": "uint128",
        "name": "_basePrice",
        "type": "uint128"
      },
      {
        "indexed": false,
        "internalType": "uint128",
        "name": "_stepPrice",
        "type": "uint128"
      },
      {
        "indexed": false,
        "internalType": "uint128",
        "name": "_startDate",
        "type": "uint128"
      }
    ],
    "name": "EditionSteppedSaleListed",
    "type": "event"
  },
  {
    "anonymous": false,
    "inputs": [
      {
        "indexed": false,
        "internalType": "address",
        "name": "account",
        "type": "address"
      }
    ],
    "name": "Paused",
    "type": "event"
  },
  {
    "anonymous": false,
    "inputs": [
      {
        "indexed": true,
        "internalType": "uint256",
        "name": "_editionId",
        "type": "uint256"
      },
      {
        "indexed": false,
        "internalType": "uint128",
        "name": "_listingPrice",
        "type": "uint128"
      },
      {
        "indexed": false,
        "internalType": "uint128",
        "name": "_startDate",
        "type": "uint128"
      }
    ],
    "name": "ReserveAuctionConvertedToBuyItNow",
    "type": "event"
  },
  {
    "anonymous": false,
    "inputs": [
      {
        "indexed": true,
        "internalType": "uint256",
        "name": "_editionId",
        "type": "uint256"
      },
      {
        "indexed": false,
        "internalType": "uint256",
        "name": "_finalPrice",
        "type": "uint256"
      },
      {
        "indexed": true,
        "internalType": "address",
        "name": "_winner",
        "type": "address"
      },
      {
        "indexed": true,
        "internalType": "address",
        "name": "_resulter",
        "type": "address"
      }
    ],
    "name": "ReserveAuctionResulted",
    "type": "event"
  },
  {
    "anonymous": false,
    "inputs": [
      {
        "indexed": true,
        "internalType": "uint256",
        "name": "_editionId",
        "type": "uint256"
      },
      {
        "indexed": false,
        "internalType": "uint256",
        "name": "_reservePrice",
        "type": "uint256"
      }
    ],
    "name": "ReservePriceUpdated",
    "type": "event"
  },
  {
    "anonymous": false,
    "inputs": [
      {
        "indexed": false,
        "internalType": "address",
        "name": "account",
        "type": "address"
      }
    ],
    "name": "Unpaused",
    "type": "event"
  },
  {
    "inputs": [
      {
        "internalType": "uint256",
        "name": "_editionId",
        "type": "uint256"
      },
      {
        "internalType": "uint256",
        "name": "_offerPrice",
        "type": "uint256"
      }
    ],
    "name": "acceptEditionBid",
    "outputs": [],
    "stateMutability": "nonpayable",
    "type": "function"
  },
  {
    "inputs": [],
    "name": "accessControls",
    "outputs": [
      {
        "internalType": "contract IKOAccessControlsLookup",
        "name": "",
        "type": "address"
      }
    ],
    "stateMutability": "view",
    "type": "function"
  },
  {
    "inputs": [
      {
        "internalType": "uint256",
        "name": "_editionId",
        "type": "uint256"
      }
    ],
    "name": "adminRejectEditionBid",
    "outputs": [],
    "stateMutability": "nonpayable",
    "type": "function"
  },
  {
    "inputs": [],
    "name": "bidLockupPeriod",
    "outputs": [
      {
        "internalType": "uint256",
        "name": "",
        "type": "uint256"
      }
    ],
    "stateMutability": "view",
    "type": "function"
  },
  {
    "inputs": [
      {
        "internalType": "uint256",
        "name": "_editionId",
        "type": "uint256"
      }
    ],
    "name": "buyEditionToken",
    "outputs": [],
    "stateMutability": "payable",
    "type": "function"
  },
  {
    "inputs": [
      {
        "internalType": "uint256",
        "name": "_editionId",
        "type": "uint256"
      },
      {
        "internalType": "address",
        "name": "_recipient",
        "type": "address"
      }
    ],
    "name": "buyEditionTokenFor",
    "outputs": [],
    "stateMutability": "payable",
    "type": "function"
  },
  {
    "inputs": [
      {
        "internalType": "uint256",
        "name": "_editionId",
        "type": "uint256"
      }
    ],
    "name": "buyNextStep",
    "outputs": [],
    "stateMutability": "payable",
    "type": "function"
  },
  {
    "inputs": [
      {
        "internalType": "uint256",
        "name": "_editionId",
        "type": "uint256"
      },
      {
        "internalType": "uint128",
        "name": "_startDate",
        "type": "uint128"
      }
    ],
    "name": "convertFromBuyNowToOffers",
    "outputs": [],
    "stateMutability": "nonpayable",
    "type": "function"
  },
  {
    "inputs": [
      {
        "internalType": "uint256",
        "name": "_editionId",
        "type": "uint256"
      },
      {
        "internalType": "uint128",
        "name": "_listingPrice",
        "type": "uint128"
      },
      {
        "internalType": "uint128",
        "name": "_startDate",
        "type": "uint128"
      }
    ],
    "name": "convertReserveAuctionToBuyItNow",
    "outputs": [],
    "stateMutability": "nonpayable",
    "type": "function"
  },
  {
    "inputs": [
      {
        "internalType": "uint256",
        "name": "_editionId",
        "type": "uint256"
      },
      {
        "internalType": "uint128",
        "name": "_listingPrice",
        "type": "uint128"
      }
    ],
    "name": "convertSteppedAuctionToListing",
    "outputs": [],
    "stateMutability": "nonpayable",
    "type": "function"
  },
  {
    "inputs": [
      {
        "internalType": "uint256",
        "name": "_editionId",
        "type": "uint256"
      }
    ],
    "name": "delistEdition",
    "outputs": [],
    "stateMutability": "nonpayable",
    "type": "function"
  },
  {
    "inputs": [
      {
        "internalType": "uint256",
        "name": "",
        "type": "uint256"
      }
    ],
    "name": "editionListings",
    "outputs": [
      {
        "internalType": "uint128",
        "name": "price",
        "type": "uint128"
      },
      {
        "internalType": "uint128",
        "name": "startDate",
        "type": "uint128"
      },
      {
        "internalType": "address",
        "name": "seller",
        "type": "address"
      }
    ],
    "stateMutability": "view",
    "type": "function"
  },
  {
    "inputs": [
      {
        "internalType": "uint256",
        "name": "",
        "type": "uint256"
      }
    ],
    "name": "editionOffers",
    "outputs": [
      {
        "internalType": "uint256",
        "name": "offer",
        "type": "uint256"
      },
      {
        "internalType": "address",
        "name": "bidder",
        "type": "address"
      },
      {
        "internalType": "uint256",
        "name": "lockupUntil",
        "type": "uint256"
      }
    ],
    "stateMutability": "view",
    "type": "function"
  },
  {
    "inputs": [
      {
        "internalType": "uint256",
        "name": "",
        "type": "uint256"
      }
    ],
    "name": "editionOffersStartDate",
    "outputs": [
      {
        "internalType": "uint256",
        "name": "",
        "type": "uint256"
      }
    ],
    "stateMutability": "view",
    "type": "function"
  },
  {
    "inputs": [
      {
        "internalType": "uint256",
        "name": "",
        "type": "uint256"
      }
    ],
    "name": "editionStep",
    "outputs": [
      {
        "internalType": "uint128",
        "name": "basePrice",
        "type": "uint128"
      },
      {
        "internalType": "uint128",
        "name": "stepPrice",
        "type": "uint128"
      },
      {
        "internalType": "uint128",
        "name": "startDate",
        "type": "uint128"
      },
      {
        "internalType": "address",
        "name": "seller",
        "type": "address"
      },
      {
        "internalType": "uint16",
        "name": "currentStep",
        "type": "uint16"
      }
    ],
    "stateMutability": "view",
    "type": "function"
  },
  {
    "inputs": [
      {
        "internalType": "uint256",
        "name": "",
        "type": "uint256"
      }
    ],
    "name": "editionWithReserveAuctions",
    "outputs": [
      {
        "internalType": "address",
        "name": "seller",
        "type": "address"
      },
      {
        "internalType": "address",
        "name": "bidder",
        "type": "address"
      },
      {
        "internalType": "uint128",
        "name": "reservePrice",
        "type": "uint128"
      },
      {
        "internalType": "uint128",
        "name": "bid",
        "type": "uint128"
      },
      {
        "internalType": "uint128",
        "name": "startDate",
        "type": "uint128"
      },
      {
        "internalType": "uint128",
        "name": "biddingEnd",
        "type": "uint128"
      }
    ],
    "stateMutability": "view",
    "type": "function"
  },
  {
    "inputs": [
      {
        "internalType": "uint256",
        "name": "_editionId",
        "type": "uint256"
      },
      {
        "internalType": "uint128",
        "name": "_startDate",
        "type": "uint128"
      }
    ],
    "name": "enableEditionOffers",
    "outputs": [],
    "stateMutability": "nonpayable",
    "type": "function"
  },
  {
    "inputs": [
      {
        "internalType": "uint256",
        "name": "_editionId",
        "type": "uint256"
      }
    ],
    "name": "getEditionListing",
    "outputs": [
      {
        "internalType": "address",
        "name": "_seller",
        "type": "address"
      },
      {
        "internalType": "uint128",
        "name": "_listingPrice",
        "type": "uint128"
      },
      {
        "internalType": "uint128",
        "name": "_startDate",
        "type": "uint128"
      }
    ],
    "stateMutability": "view",
    "type": "function"
  },
  {
    "inputs": [
      {
        "internalType": "uint256",
        "name": "_editionId",
        "type": "uint256"
      }
    ],
    "name": "getEditionListingDate",
    "outputs": [
      {
        "internalType": "uint128",
        "name": "_startDate",
        "type": "uint128"
      }
    ],
    "stateMutability": "view",
    "type": "function"
  },
  {
    "inputs": [
      {
        "internalType": "uint256",
        "name": "_editionId",
        "type": "uint256"
      }
    ],
    "name": "getEditionListingPrice",
    "outputs": [
      {
        "internalType": "uint128",
        "name": "_listingPrice",
        "type": "uint128"
      }
    ],
    "stateMutability": "view",
    "type": "function"
  },
  {
    "inputs": [
      {
        "internalType": "uint256",
        "name": "_editionId",
        "type": "uint256"
      }
    ],
    "name": "getEditionListingSeller",
    "outputs": [
      {
        "internalType": "address",
        "name": "_seller",
        "type": "address"
      }
    ],
    "stateMutability": "view",
    "type": "function"
  },
  {
    "inputs": [
      {
        "internalType": "uint256",
        "name": "_editionId",
        "type": "uint256"
      }
    ],
    "name": "getNextEditionSteppedPrice",
    "outputs": [
      {
        "internalType": "uint256",
        "name": "price",
        "type": "uint256"
      }
    ],
    "stateMutability": "view",
    "type": "function"
  },
  {
    "inputs": [
      {
        "internalType": "uint256",
        "name": "_editionId",
        "type": "uint256"
      }
    ],
    "name": "getSteppedAuctionState",
    "outputs": [
      {
        "internalType": "address",
        "name": "creator",
        "type": "address"
      },
      {
        "internalType": "uint128",
        "name": "basePrice",
        "type": "uint128"
      },
      {
        "internalType": "uint128",
        "name": "stepPrice",
        "type": "uint128"
      },
      {
        "internalType": "uint128",
        "name": "startDate",
        "type": "uint128"
      },
      {
        "internalType": "uint16",
        "name": "currentStep",
        "type": "uint16"
      }
    ],
    "stateMutability": "view",
    "type": "function"
  },
  {
    "inputs": [],
    "name": "koda",
    "outputs": [
      {
        "internalType": "contract IKODAV3",
        "name": "",
        "type": "address"
      }
    ],
    "stateMutability": "view",
    "type": "function"
  },
  {
    "inputs": [
      {
        "internalType": "address",
        "name": "_creator",
        "type": "address"
      },
      {
        "internalType": "uint256",
        "name": "_editionId",
        "type": "uint256"
      },
      {
        "internalType": "uint128",
        "name": "_listingPrice",
        "type": "uint128"
      },
      {
        "internalType": "uint128",
        "name": "_startDate",
        "type": "uint128"
      }
    ],
    "name": "listEdition",
    "outputs": [],
    "stateMutability": "nonpayable",
    "type": "function"
  },
  {
    "inputs": [
      {
        "internalType": "address",
        "name": "_creator",
        "type": "address"
      },
      {
        "internalType": "uint256",
        "name": "_editionId",
        "type": "uint256"
      },
      {
        "internalType": "uint128",
        "name": "_reservePrice",
        "type": "uint128"
      },
      {
        "internalType": "uint128",
        "name": "_startDate",
        "type": "uint128"
      }
    ],
    "name": "listEditionForReserveAuction",
    "outputs": [],
    "stateMutability": "nonpayable",
    "type": "function"
  },
  {
    "inputs": [
      {
        "internalType": "address",
        "name": "_creator",
        "type": "address"
      },
      {
        "internalType": "uint256",
        "name": "_editionId",
        "type": "uint256"
      },
      {
        "internalType": "uint128",
        "name": "_basePrice",
        "type": "uint128"
      },
      {
        "internalType": "uint128",
        "name": "_stepPrice",
        "type": "uint128"
      },
      {
        "internalType": "uint128",
        "name": "_startDate",
        "type": "uint128"
      }
    ],
    "name": "listSteppedEditionAuction",
    "outputs": [],
    "stateMutability": "nonpayable",
    "type": "function"
  },
  {
    "inputs": [],
    "name": "minBidAmount",
    "outputs": [
      {
        "internalType": "uint256",
        "name": "",
        "type": "uint256"
      }
    ],
    "stateMutability": "view",
    "type": "function"
  },
  {
    "inputs": [],
    "name": "modulo",
    "outputs": [
      {
        "internalType": "uint256",
        "name": "",
        "type": "uint256"
      }
    ],
    "stateMutability": "view",
    "type": "function"
  },
  {
    "inputs": [],
    "name": "pause",
    "outputs": [],
    "stateMutability": "nonpayable",
    "type": "function"
  },
  {
    "inputs": [],
    "name": "paused",
    "outputs": [
      {
        "internalType": "bool",
        "name": "",
        "type": "bool"
      }
    ],
    "stateMutability": "view",
    "type": "function"
  },
  {
    "inputs": [
      {
        "internalType": "uint256",
        "name": "_editionId",
        "type": "uint256"
      }
    ],
    "name": "placeBidOnReserveAuction",
    "outputs": [],
    "stateMutability": "payable",
    "type": "function"
  },
  {
    "inputs": [
      {
        "internalType": "uint256",
        "name": "_editionId",
        "type": "uint256"
      }
    ],
    "name": "placeEditionBid",
    "outputs": [],
    "stateMutability": "payable",
    "type": "function"
  },
  {
    "inputs": [],
    "name": "platformAccount",
    "outputs": [
      {
        "internalType": "address",
        "name": "",
        "type": "address"
      }
    ],
    "stateMutability": "view",
    "type": "function"
  },
  {
    "inputs": [],
    "name": "platformPrimarySaleCommission",
    "outputs": [
      {
        "internalType": "uint256",
        "name": "",
        "type": "uint256"
      }
    ],
    "stateMutability": "view",
    "type": "function"
  },
  {
    "inputs": [
      {
        "internalType": "uint256",
        "name": "_editionId",
        "type": "uint256"
      }
    ],
    "name": "rejectEditionBid",
    "outputs": [],
    "stateMutability": "nonpayable",
    "type": "function"
  },
  {
    "inputs": [],
    "name": "reserveAuctionBidExtensionWindow",
    "outputs": [
      {
        "internalType": "uint128",
        "name": "",
        "type": "uint128"
      }
    ],
    "stateMutability": "view",
    "type": "function"
  },
  {
    "inputs": [],
    "name": "reserveAuctionLengthOnceReserveMet",
    "outputs": [
      {
        "internalType": "uint128",
        "name": "",
        "type": "uint128"
      }
    ],
    "stateMutability": "view",
    "type": "function"
  },
  {
    "inputs": [
      {
        "internalType": "uint256",
        "name": "_editionId",
        "type": "uint256"
      }
    ],
    "name": "resultReserveAuction",
    "outputs": [],
    "stateMutability": "nonpayable",
    "type": "function"
  },
  {
    "inputs": [
      {
        "internalType": "uint256",
        "name": "_editionId",
        "type": "uint256"
      },
      {
        "internalType": "uint128",
        "name": "_listingPrice",
        "type": "uint128"
      }
    ],
    "name": "setEditionPriceListing",
    "outputs": [],
    "stateMutability": "nonpayable",
    "type": "function"
  },
  {
    "inputs": [],
    "name": "unpause",
    "outputs": [],
    "stateMutability": "nonpayable",
    "type": "function"
  },
  {
    "inputs": [
      {
        "internalType": "uint256",
        "name": "_minBidAmount",
        "type": "uint256"
      }
    ],
    "name": "updateMinBidAmount",
    "outputs": [],
    "stateMutability": "nonpayable",
    "type": "function"
  },
  {
    "inputs": [
      {
        "internalType": "uint256",
        "name": "_modulo",
        "type": "uint256"
      }
    ],
    "name": "updateModulo",
    "outputs": [],
    "stateMutability": "nonpayable",
    "type": "function"
  },
  {
    "inputs": [
      {
        "internalType": "uint256",
        "name": "_platformPrimarySaleCommission",
        "type": "uint256"
      }
    ],
    "name": "updatePlatformPrimarySaleCommission",
    "outputs": [],
    "stateMutability": "nonpayable",
    "type": "function"
  },
  {
    "inputs": [
      {
        "internalType": "uint128",
        "name": "_reserveAuctionBidExtensionWindow",
        "type": "uint128"
      }
    ],
    "name": "updateReserveAuctionBidExtensionWindow",
    "outputs": [],
    "stateMutability": "nonpayable",
    "type": "function"
  },
  {
    "inputs": [
      {
        "internalType": "uint128",
        "name": "_reserveAuctionLengthOnceReserveMet",
        "type": "uint128"
      }
    ],
    "name": "updateReserveAuctionLengthOnceReserveMet",
    "outputs": [],
    "stateMutability": "nonpayable",
    "type": "function"
  },
  {
    "inputs": [
      {
        "internalType": "uint256",
        "name": "_editionId",
        "type": "uint256"
      },
      {
        "internalType": "uint128",
        "name": "_reservePrice",
        "type": "uint128"
      }
    ],
    "name": "updateReservePriceForReserveAuction",
    "outputs": [],
    "stateMutability": "nonpayable",
    "type": "function"
  },
  {
    "inputs": [
      {
        "internalType": "uint256",
        "name": "_editionId",
        "type": "uint256"
      }
    ],
    "name": "withdrawBidFromReserveAuction",
    "outputs": [],
    "stateMutability": "nonpayable",
    "type": "function"
  },
  {
    "inputs": [
      {
        "internalType": "uint256",
        "name": "_editionId",
        "type": "uint256"
      }
    ],
    "name": "withdrawEditionBid",
    "outputs": [],
    "stateMutability": "nonpayable",
    "type": "function"
  }
]
